{
    "level": 5,
    "lstProcessData": [
        {
            "process": 0,
            "boxDifficulty": {
                "name": "Easy",
                "easePercent": 100,
                "normalPercent": 0,
                "hardPercent": 0
            }
        },
        {
            "process": 50,
            "boxDifficulty": {
                "name": "Trick 2",
                "easePercent": 75,
                "normalPercent": 15,
                "hardPercent": 10
            }
        }
    ]
}